loki/__init__.py
loki/io_options.py
loki/xml/__init__.py
loki/xml/cut.py
loki/xml/find.py
loki/xml/format.py
loki/xml/strip.py
loki/xml/utils.py
loki_utils-0.0.3.dist-info/LICENSE
loki_utils-0.0.3.dist-info/METADATA
loki_utils-0.0.3.dist-info/WHEEL
loki_utils-0.0.3.dist-info/entry_points.txt
loki_utils-0.0.3.dist-info/top_level.txt
loki_utils-0.0.3.dist-info/RECORD
