Metadata-Version: 2.1
Name: loki-utils
Version: 0.0.3
Author: Mathias Örtenberg Toftås
Maintainer: Mathias Örtenberg Toftås
License: MIT License
Project-URL: Repository, https://github.com/MathiasToftas/loki
Keywords: parsing,xml
License-File: LICENSE
Requires-Dist: click
Requires-Dist: Levenshtein
Provides-Extra: dev
Requires-Dist: pre-commit; extra == "dev"
Requires-Dist: build; extra == "dev"
Requires-Dist: twine; extra == "dev"
